notion/__init__.py
notion/id_worker.py
notion/markdown.py
notion/processor.py
notion_hugo-0.2.4.dist-info/LICENSE
notion_hugo-0.2.4.dist-info/METADATA
notion_hugo-0.2.4.dist-info/WHEEL
notion_hugo-0.2.4.dist-info/top_level.txt
notion_hugo-0.2.4.dist-info/RECORD
