Metadata-Version: 2.1
Name: notion-hugo
Version: 0.2.4
Summary: convert notion page content to markdown
Home-page: https://github.com/gclm/notion-hugo
Author: gclm
Author-email: gclmit@163.com
License: UNKNOWN
Platform: UNKNOWN
Classifier: Programming Language :: Python :: 3.7
Classifier: Programming Language :: Python :: 3.8
Classifier: Programming Language :: Python :: 3.9
Classifier: License :: OSI Approved :: Apache Software License
Classifier: Operating System :: OS Independent
License-File: LICENSE
Requires-Dist: notion-client
Requires-Dist: markdown
